huaweicloudsdkiotdm/__init__.py
huaweicloudsdkiotdm/v5/__init__.py
huaweicloudsdkiotdm/v5/iotdm_async_client.py
huaweicloudsdkiotdm/v5/iotdm_client.py
huaweicloudsdkiotdm/v5/model/__init__.py
huaweicloudsdkiotdm/v5/model/access_info.py
huaweicloudsdkiotdm/v5/model/additional_params.py
huaweicloudsdkiotdm/v5/model/additional_params_resp.py
huaweicloudsdkiotdm/v5/model/bind_instance_tags.py
huaweicloudsdkiotdm/v5/model/bind_instance_tags_request.py
huaweicloudsdkiotdm/v5/model/bind_instance_tags_response.py
huaweicloudsdkiotdm/v5/model/change_instance_charge_mode.py
huaweicloudsdkiotdm/v5/model/change_instance_charge_mode_request.py
huaweicloudsdkiotdm/v5/model/change_instance_charge_mode_response.py
huaweicloudsdkiotdm/v5/model/charge_info.py
huaweicloudsdkiotdm/v5/model/create_instance.py
huaweicloudsdkiotdm/v5/model/create_instance_request.py
huaweicloudsdkiotdm/v5/model/create_instance_response.py
huaweicloudsdkiotdm/v5/model/delete_instance_request.py
huaweicloudsdkiotdm/v5/model/delete_instance_response.py
huaweicloudsdkiotdm/v5/model/flavor.py
huaweicloudsdkiotdm/v5/model/forwarding_info.py
huaweicloudsdkiotdm/v5/model/instance_flavor.py
huaweicloudsdkiotdm/v5/model/instance_task.py
huaweicloudsdkiotdm/v5/model/ip_allow_list.py
huaweicloudsdkiotdm/v5/model/ip_white_list.py
huaweicloudsdkiotdm/v5/model/list_instance_flavors_request.py
huaweicloudsdkiotdm/v5/model/list_instance_flavors_response.py
huaweicloudsdkiotdm/v5/model/list_instance_tasks_request.py
huaweicloudsdkiotdm/v5/model/list_instance_tasks_response.py
huaweicloudsdkiotdm/v5/model/list_instances_request.py
huaweicloudsdkiotdm/v5/model/list_instances_response.py
huaweicloudsdkiotdm/v5/model/operate_window.py
huaweicloudsdkiotdm/v5/model/page.py
huaweicloudsdkiotdm/v5/model/port.py
huaweicloudsdkiotdm/v5/model/query_instance_simplify.py
huaweicloudsdkiotdm/v5/model/resize_instance.py
huaweicloudsdkiotdm/v5/model/resize_instance_request.py
huaweicloudsdkiotdm/v5/model/resize_instance_response.py
huaweicloudsdkiotdm-3.1.184.dist-info/METADATA
huaweicloudsdkiotdm-3.1.184.dist-info/WHEEL
huaweicloudsdkiotdm-3.1.184.dist-info/licenses/LICENSE
huaweicloudsdkiotdm-3.1.184.dist-info/RECORD
